encrypter_decrypter/__init__.py
encrypter_decrypter/enc_tool.py
encrypter_decrypter/main.py
encrypter_decrypter/test.py
encrypter_decrypter/config/__init__.py
encrypter_decrypter/config/config.py
enc_tool-1.1.2.dist-info/METADATA
enc_tool-1.1.2.dist-info/WHEEL
enc_tool-1.1.2.dist-info/entry_points.txt
enc_tool-1.1.2.dist-info/top_level.txt
enc_tool-1.1.2.dist-info/RECORD
