Metadata-Version: 2.1
Name: enc-tool
Version: 1.1.2
Summary: A tool to encrypt and decrypt your data! Use it to make your messages and files safe...
Author: Night Error
Author-email: night.error.go@gmail.com
Requires-Dist: colorama
Requires-Dist: cryptography
